LICENSE.txt
MANIFEST.in
README.rst
setup.cfg
setup.py
cnex_dfx/__init__.py
cnex_dfx/interface.py
cnex_dfx/run.py
cnex_dfx.egg-info/PKG-INFO
cnex_dfx.egg-info/SOURCES.txt
cnex_dfx.egg-info/dependency_links.txt
cnex_dfx.egg-info/entry_points.txt
cnex_dfx.egg-info/top_level.txt
cnex_dfx/configuration/ecc_enc.dfx
cnex_dfx/configuration/err_chk.dfx
cnex_dfx/configuration/nsc_gc.dfx
cnex_dfx/configuration/nsc_read.dfx
cnex_dfx/configuration/nsc_read_4ch.dfx
cnex_dfx/configuration/nsc_read_8ch.dfx
cnex_dfx/configuration/nsc_write.dfx
cnex_dfx/configuration/nvc.dfx
cnex_dfx/lib/__init__.py
cnex_dfx/lib/dump.py
cnex_dfx/lib/executor.py
cnex_dfx/lib/parsing.py
cnex_dfx/lib/state.py
cnex_dfx/lib/driver/__init__.py
cnex_dfx/lib/driver/nvme.py
cnex_dfx/lib/driver/pcie.py