Metadata-Version: 1.1
Name: cnex-dfx
Version: 2.2.3
Summary: cnexlabs tool for dump dfx files
Home-page: https://pypi.org/project/cnex_dfx
Author: yuwen123441
Author-email: yuwen123441@qq.com
License: MIT License
Keywords: cnexlabs,dfx,dump
Platform: any
Classifier: Development Status :: 3 - Alpha
Classifier: Intended Audience :: Developers
Classifier: Topic :: Software Development :: Libraries
Classifier: License :: OSI Approved :: MIT License
Classifier: Programming Language :: Python :: 3.6
